qtier/__init__.py
qtier/autoproperty.py
qtier/exceptions.py
qtier/ext/__init__.py
qtier/ext/mypy_plugin.py
qtier/gql/__init__.py
qtier/gql/client.py
qtier/gql/gqlcore.py
qtier/itemsystem/__init__.py
qtier/itemsystem/_core.py
qtier/py.typed
qtier/slot.py
qtier/typingref.py
qtier-0.1.0.dist-info/WHEEL
qtier-0.1.0.dist-info/LICENSE
qtier-0.1.0.dist-info/METADATA
qtier-0.1.0.dist-info/RECORD
