Metadata-Version: 2.1
Name: qtier
Version: 0.1.0
Summary: Cuter approuch to Qt-for-python, with focus on type hints.
License: MIT
Author: Nir
Author-email: 88795475+nrbnlulu@users.noreply.github.com
Requires-Python: >=3.10,<3.12
Classifier: License :: OSI Approved :: MIT License
Classifier: Programming Language :: Python :: 3
Classifier: Programming Language :: Python :: 3.10
Classifier: Programming Language :: Python :: 3.11
Requires-Dist: PySide6 (>=6.4.1,<7.0.0)
Requires-Dist: QtPy (>=2.3.0,<3.0.0)
Requires-Dist: attrs (>=22.1.0,<23.0.0)
